isgd/__init__.py
isgd-0.2.1.dist-info/WHEEL
isgd-0.2.1.dist-info/METADATA
isgd-0.2.1.dist-info/RECORD
