Metadata-Version: 2.1
Name: isgd
Version: 0.2.1
Summary: 🔗 A CLI to shorten url(s) using is.gd/v.gd
Author: nitr7gen
Author-email: nitr7gen@proton.me
Requires-Python: >=3.10,<4.0
Classifier: Programming Language :: Python :: 3
Classifier: Programming Language :: Python :: 3.10
Classifier: Programming Language :: Python :: 3.11
Requires-Dist: typer[all] (>=0.6.1,<0.7.0)
